yamldoc/__init__.py
yamldoc/cli.py
yamldoc/entries.py
yamldoc/parser.py
yamldoc-0.1.6.dist-info/LICENSE
yamldoc-0.1.6.dist-info/METADATA
yamldoc-0.1.6.dist-info/WHEEL
yamldoc-0.1.6.dist-info/entry_points.txt
yamldoc-0.1.6.dist-info/top_level.txt
yamldoc-0.1.6.dist-info/RECORD
