Metadata-Version: 2.1
Name: yamldoc
Version: 0.1.6
Summary: Documentation engine for YAML.
Home-page: UNKNOWN
Author: Chris Cole
Author-email: ccole@well.ox.ac.uk
License: UNKNOWN
Platform: UNKNOWN
License-File: LICENSE
